{
  "clear_gop_structure": {
    "bbls": {
      "49": {
        "called_fns": [
          "dataReadCacheCallback"
        ],
        "in_edges": [],
        "out_edges": [
          51,
          50
        ],
        "weight": 2
      },
      "50": {
        "called_fns": [
          "free"
        ],
        "in_edges": [
          49
        ],
        "out_edges": [],
        "weight": 1
      },
      "51": {
        "called_fns": [],
        "in_edges": [
          49
        ],
        "out_edges": [],
        "weight": 1
      }
    },
    "entry_block": 49,
    "loops": {},
    "returning_blocks": [
      50,
      51
    ]
  },
  "create_pyramid": {
    "bbls": {
      "1": {
        "called_fns": [
          "dataReadCacheCallback",
          "dataReadCacheCallback",
          "dataReadCacheCallback"
        ],
        "in_edges": [],
        "out_edges": [
          2,
          5
        ],
        "weight": 6
      },
      "10": {
        "called_fns": [],
        "in_edges": [
          8,
          9
        ],
        "out_edges": [
          11,
          17
        ],
        "weight": 1
      },
      "11": {
        "called_fns": [
          "dataReadCacheCallback"
        ],
        "in_edges": [
          10
        ],
        "out_edges": [
          12,
          13
        ],
        "weight": 3
      },
      "12": {
        "called_fns": [],
        "in_edges": [
          11
        ],
        "out_edges": [
          17,
          16
        ],
        "weight": 1
      },
      "13": {
        "called_fns": [],
        "in_edges": [
          11
        ],
        "out_edges": [
          14
        ],
        "weight": 4
      },
      "14": {
        "called_fns": [
          "dataWriteCacheCallback",
          "dataWriteCacheCallback",
          "dataWriteCacheCallback",
          "dataWriteCacheCallback"
        ],
        "in_edges": [
          13,
          14
        ],
        "out_edges": [
          15,
          14
        ],
        "weight": 6
      },
      "15": {
        "called_fns": [],
        "in_edges": [
          14
        ],
        "out_edges": [
          17,
          16
        ],
        "weight": 1
      },
      "16": {
        "called_fns": [
          "dataWriteCacheCallback",
          "dataWriteCacheCallback"
        ],
        "in_edges": [
          15,
          12
        ],
        "out_edges": [
          17
        ],
        "weight": 4
      },
      "17": {
        "called_fns": [],
        "in_edges": [
          10,
          15,
          16,
          12
        ],
        "out_edges": [
          18,
          20
        ],
        "weight": 1
      },
      "18": {
        "called_fns": [],
        "in_edges": [
          17
        ],
        "out_edges": [
          19
        ],
        "weight": 1
      },
      "19": {
        "called_fns": [
          "dataWriteCacheCallback"
        ],
        "in_edges": [
          19,
          18
        ],
        "out_edges": [
          19,
          21
        ],
        "weight": 4
      },
      "2": {
        "called_fns": [],
        "in_edges": [
          1
        ],
        "out_edges": [
          3,
          34
        ],
        "weight": 1
      },
      "20": {
        "called_fns": [],
        "in_edges": [
          17
        ],
        "out_edges": [
          21
        ],
        "weight": 1
      },
      "21": {
        "called_fns": [
          "dataWriteCacheCallback"
        ],
        "in_edges": [
          19,
          20
        ],
        "out_edges": [
          22,
          25
        ],
        "weight": 5
      },
      "22": {
        "called_fns": [
          "dataReadCacheCallback"
        ],
        "in_edges": [
          21
        ],
        "out_edges": [
          23
        ],
        "weight": 4
      },
      "23": {
        "called_fns": [
          "dataReadCacheCallback",
          "gop_pyramid"
        ],
        "in_edges": [
          22,
          23
        ],
        "out_edges": [
          24,
          23
        ],
        "weight": 4
      },
      "24": {
        "called_fns": [
          "dataReadCacheCallback",
          "dataReadCacheCallback"
        ],
        "in_edges": [
          23
        ],
        "out_edges": [
          25
        ],
        "weight": 2
      },
      "25": {
        "called_fns": [],
        "in_edges": [
          21,
          24
        ],
        "out_edges": [
          26,
          34
        ],
        "weight": 1
      },
      "26": {
        "called_fns": [
          "dataReadCacheCallback"
        ],
        "in_edges": [
          25
        ],
        "out_edges": [
          29,
          27
        ],
        "weight": 4
      },
      "27": {
        "called_fns": [],
        "in_edges": [
          28,
          31,
          26
        ],
        "out_edges": [
          28,
          34
        ],
        "weight": 1
      },
      "28": {
        "called_fns": [],
        "in_edges": [
          27
        ],
        "out_edges": [
          29,
          27
        ],
        "weight": 1
      },
      "29": {
        "called_fns": [
          "dataReadCacheCallback"
        ],
        "in_edges": [
          28,
          26
        ],
        "out_edges": [
          32
        ],
        "weight": 4
      },
      "3": {
        "called_fns": [
          "dataReadCacheCallback"
        ],
        "in_edges": [
          2
        ],
        "out_edges": [
          4
        ],
        "weight": 8
      },
      "30": {
        "called_fns": [
          "dataReadCacheCallback",
          "dataWriteCacheCallback",
          "dataWriteCacheCallback",
          "dataReadCacheCallback",
          "dataWriteCacheCallback",
          "dataWriteCacheCallback",
          "dataReadCacheCallback",
          "dataReadCacheCallback",
          "dataWriteCacheCallback",
          "dataWriteCacheCallback"
        ],
        "in_edges": [
          32
        ],
        "out_edges": [
          31
        ],
        "weight": 13
      },
      "31": {
        "called_fns": [],
        "in_edges": [
          30,
          33
        ],
        "out_edges": [
          27,
          32
        ],
        "weight": 2
      },
      "32": {
        "called_fns": [
          "dataReadCacheCallback"
        ],
        "in_edges": [
          29,
          31
        ],
        "out_edges": [
          30,
          33
        ],
        "weight": 2
      },
      "33": {
        "called_fns": [],
        "in_edges": [
          32
        ],
        "out_edges": [
          31
        ],
        "weight": 1
      },
      "34": {
        "called_fns": [],
        "in_edges": [
          25,
          27,
          2,
          4
        ],
        "out_edges": [],
        "weight": 2
      },
      "4": {
        "called_fns": [
          "dataWriteCacheCallback",
          "dataWriteCacheCallback",
          "dataWriteCacheCallback",
          "dataWriteCacheCallback"
        ],
        "in_edges": [
          3,
          4
        ],
        "out_edges": [
          34,
          4
        ],
        "weight": 11
      },
      "5": {
        "called_fns": [],
        "in_edges": [
          1
        ],
        "out_edges": [
          6,
          8
        ],
        "weight": 1
      },
      "6": {
        "called_fns": [],
        "in_edges": [
          5
        ],
        "out_edges": [
          7
        ],
        "weight": 1
      },
      "7": {
        "called_fns": [],
        "in_edges": [
          6,
          7
        ],
        "out_edges": [
          7,
          8
        ],
        "weight": 2
      },
      "8": {
        "called_fns": [
          "malloc"
        ],
        "in_edges": [
          5,
          7
        ],
        "out_edges": [
          9,
          10
        ],
        "weight": 2
      },
      "9": {
        "called_fns": [
          "no_mem_exit",
          "dataReadCacheCallback",
          "dataReadCacheCallback"
        ],
        "in_edges": [
          8
        ],
        "out_edges": [
          10
        ],
        "weight": 2
      }
    },
    "entry_block": 1,
    "loops": {
      "1": {
        "loop_called_fns": [
          "dataWriteCacheCallback"
        ],
        "loop_headers": [
          4
        ],
        "loop_latches": [
          4
        ]
      },
      "2": {
        "loop_called_fns": [
          "dataWriteCacheCallback"
        ],
        "loop_headers": [
          14
        ],
        "loop_latches": [
          14
        ]
      },
      "3": {
        "loop_called_fns": [
          "dataReadCacheCallback",
          "gop_pyramid"
        ],
        "loop_headers": [
          23
        ],
        "loop_latches": [
          23
        ]
      },
      "4": {
        "loop_called_fns": [
          "dataReadCacheCallback",
          "dataWriteCacheCallback"
        ],
        "loop_headers": [
          32
        ],
        "loop_latches": [
          31
        ]
      }
    },
    "returning_blocks": [
      34
    ]
  },
  "encode_enhancement_layer": {
    "bbls": {
      "111": {
        "called_fns": [
          "dataReadCacheCallback",
          "dataReadCacheCallback",
          "dataReadCacheCallback"
        ],
        "in_edges": [],
        "out_edges": [
          155,
          112
        ],
        "weight": 7
      },
      "112": {
        "called_fns": [
          "dataReadCacheCallback",
          "dataReadCacheCallback"
        ],
        "in_edges": [
          111
        ],
        "out_edges": [
          113,
          155
        ],
        "weight": 2
      },
      "113": {
        "called_fns": [
          "dataWriteCacheCallback",
          "dataReadCacheCallback",
          "dataWriteCacheCallback",
          "dataReadCacheCallback",
          "dataReadCacheCallback"
        ],
        "in_edges": [
          112
        ],
        "out_edges": [
          116,
          114
        ],
        "weight": 6
      },
      "114": {
        "called_fns": [
          "dataWriteCacheCallback",
          "dataWriteCacheCallback"
        ],
        "in_edges": [
          113
        ],
        "out_edges": [
          138,
          115
        ],
        "weight": 3
      },
      "115": {
        "called_fns": [],
        "in_edges": [
          114
        ],
        "out_edges": [
          136,
          118
        ],
        "weight": 1
      },
      "116": {
        "called_fns": [],
        "in_edges": [
          113
        ],
        "out_edges": [
          137,
          117
        ],
        "weight": 1
      },
      "117": {
        "called_fns": [
          "dataWriteCacheCallback",
          "dataWriteCacheCallback"
        ],
        "in_edges": [
          116
        ],
        "out_edges": [
          136,
          118
        ],
        "weight": 3
      },
      "118": {
        "called_fns": [],
        "in_edges": [
          115,
          117
        ],
        "out_edges": [
          120
        ],
        "weight": 1
      },
      "119": {
        "called_fns": [
          "dataReadCacheCallback",
          "dataReadCacheCallback",
          "dataWriteCacheCallback",
          "dataReadCacheCallback"
        ],
        "in_edges": [
          134,
          135
        ],
        "out_edges": [
          120,
          136
        ],
        "weight": 5
      },
      "120": {
        "called_fns": [
          "dataWriteCacheCallback",
          "dataReadCacheCallback",
          "dataReadCacheCallback",
          "dataWriteCacheCallback",
          "dataReadCacheCallback"
        ],
        "in_edges": [
          118,
          119
        ],
        "out_edges": [
          121,
          122
        ],
        "weight": 8
      },
      "121": {
        "called_fns": [
          "dataWriteCacheCallback",
          "dataReadCacheCallback",
          "dataReadCacheCallback",
          "dataWriteCacheCallback"
        ],
        "in_edges": [
          120
        ],
        "out_edges": [
          122
        ],
        "weight": 8
      },
      "122": {
        "called_fns": [
          "dataReadCacheCallback",
          "dataWriteCacheCallback",
          "dataReadCacheCallback"
        ],
        "in_edges": [
          120,
          121
        ],
        "out_edges": [
          123,
          124
        ],
        "weight": 13
      },
      "123": {
        "called_fns": [],
        "in_edges": [
          122
        ],
        "out_edges": [
          124
        ],
        "weight": 1
      },
      "124": {
        "called_fns": [
          "dataWriteCacheCallback",
          "dataReadCacheCallback"
        ],
        "in_edges": [
          122,
          123
        ],
        "out_edges": [
          127,
          125
        ],
        "weight": 3
      },
      "125": {
        "called_fns": [
          "dataReadCacheCallback"
        ],
        "in_edges": [
          124
        ],
        "out_edges": [
          127,
          126
        ],
        "weight": 1
      },
      "126": {
        "called_fns": [
          "dataReadCacheCallback",
          "dataReadCacheCallback",
          "dataReadCacheCallback",
          "dataWriteCacheCallback"
        ],
        "in_edges": [
          125
        ],
        "out_edges": [
          128
        ],
        "weight": 23
      },
      "127": {
        "called_fns": [
          "dataReadCacheCallback",
          "dataReadCacheCallback",
          "dataReadCacheCallback",
          "dataWriteCacheCallback"
        ],
        "in_edges": [
          125,
          124
        ],
        "out_edges": [
          128
        ],
        "weight": 14
      },
      "128": {
        "called_fns": [
          "dataReadCacheCallback"
        ],
        "in_edges": [
          127,
          126
        ],
        "out_edges": [
          129,
          130
        ],
        "weight": 2
      },
      "129": {
        "called_fns": [],
        "in_edges": [
          128
        ],
        "out_edges": [
          131
        ],
        "weight": 1
      },
      "130": {
        "called_fns": [
          "dataReadCacheCallback"
        ],
        "in_edges": [
          128
        ],
        "out_edges": [
          131
        ],
        "weight": 12
      },
      "131": {
        "called_fns": [
          "dataWriteCacheCallback",
          "dataReadCacheCallback"
        ],
        "in_edges": [
          130,
          129
        ],
        "out_edges": [
          132,
          133
        ],
        "weight": 5
      },
      "132": {
        "called_fns": [
          "dataReadCacheCallback"
        ],
        "in_edges": [
          131
        ],
        "out_edges": [
          134,
          133
        ],
        "weight": 1
      },
      "133": {
        "called_fns": [],
        "in_edges": [
          132,
          131
        ],
        "out_edges": [
          134
        ],
        "weight": 1
      },
      "134": {
        "called_fns": [
          "dataWriteCacheCallback",
          "dataWriteCacheCallback",
          "dataWriteCacheCallback",
          "encode_one_frame",
          "dataReadCacheCallback",
          "dataReadCacheCallback"
        ],
        "in_edges": [
          132,
          133
        ],
        "out_edges": [
          119,
          135
        ],
        "weight": 7
      },
      "135": {
        "called_fns": [
          "report_frame_statistic",
          "dataReadCacheCallback"
        ],
        "in_edges": [
          134
        ],
        "out_edges": [
          119
        ],
        "weight": 2
      },
      "136": {
        "called_fns": [
          "dataWriteCacheCallback"
        ],
        "in_edges": [
          115,
          119,
          117
        ],
        "out_edges": [
          155
        ],
        "weight": 1
      },
      "137": {
        "called_fns": [
          "dataReadCacheCallback",
          "dataReadCacheCallback",
          "dataWriteCacheCallback",
          "dataWriteCacheCallback",
          "dataWriteCacheCallback"
        ],
        "in_edges": [
          116
        ],
        "out_edges": [
          138
        ],
        "weight": 9
      },
      "138": {
        "called_fns": [],
        "in_edges": [
          114,
          137
        ],
        "out_edges": [
          155,
          139
        ],
        "weight": 1
      },
      "139": {
        "called_fns": [],
        "in_edges": [
          138
        ],
        "out_edges": [
          140
        ],
        "weight": 1
      },
      "140": {
        "called_fns": [
          "dataWriteCacheCallback"
        ],
        "in_edges": [
          139,
          154
        ],
        "out_edges": [
          141,
          142
        ],
        "weight": 2
      },
      "141": {
        "called_fns": [
          "dataWriteCacheCallback",
          "dataReadCacheCallback",
          "dataReadCacheCallback",
          "dataWriteCacheCallback"
        ],
        "in_edges": [
          140
        ],
        "out_edges": [
          142
        ],
        "weight": 7
      },
      "142": {
        "called_fns": [
          "dataReadCacheCallback",
          "dataWriteCacheCallback",
          "dataReadCacheCallback"
        ],
        "in_edges": [
          140,
          141
        ],
        "out_edges": [
          143,
          144
        ],
        "weight": 13
      },
      "143": {
        "called_fns": [],
        "in_edges": [
          142
        ],
        "out_edges": [
          144
        ],
        "weight": 1
      },
      "144": {
        "called_fns": [
          "dataWriteCacheCallback",
          "dataReadCacheCallback"
        ],
        "in_edges": [
          142,
          143
        ],
        "out_edges": [
          147,
          145
        ],
        "weight": 3
      },
      "145": {
        "called_fns": [
          "dataReadCacheCallback"
        ],
        "in_edges": [
          144
        ],
        "out_edges": [
          147,
          146
        ],
        "weight": 1
      },
      "146": {
        "called_fns": [
          "dataReadCacheCallback",
          "dataReadCacheCallback"
        ],
        "in_edges": [
          145
        ],
        "out_edges": [
          148
        ],
        "weight": 13
      },
      "147": {
        "called_fns": [
          "dataReadCacheCallback",
          "dataReadCacheCallback"
        ],
        "in_edges": [
          145,
          144
        ],
        "out_edges": [
          148
        ],
        "weight": 3
      },
      "148": {
        "called_fns": [
          "dataWriteCacheCallback",
          "dataReadCacheCallback"
        ],
        "in_edges": [
          146,
          147
        ],
        "out_edges": [
          149,
          150
        ],
        "weight": 9
      },
      "149": {
        "called_fns": [
          "dataReadCacheCallback"
        ],
        "in_edges": [
          148
        ],
        "out_edges": [
          151,
          150
        ],
        "weight": 1
      },
      "150": {
        "called_fns": [],
        "in_edges": [
          148,
          149
        ],
        "out_edges": [
          151
        ],
        "weight": 1
      },
      "151": {
        "called_fns": [
          "dataWriteCacheCallback",
          "dataWriteCacheCallback",
          "dataWriteCacheCallback",
          "dataWriteCacheCallback",
          "encode_one_frame",
          "dataReadCacheCallback",
          "dataReadCacheCallback"
        ],
        "in_edges": [
          149,
          150
        ],
        "out_edges": [
          153,
          152
        ],
        "weight": 9
      },
      "152": {
        "called_fns": [
          "report_frame_statistic",
          "dataReadCacheCallback"
        ],
        "in_edges": [
          151
        ],
        "out_edges": [
          153
        ],
        "weight": 2
      },
      "153": {
        "called_fns": [
          "dataReadCacheCallback",
          "dataReadCacheCallback",
          "dataWriteCacheCallback",
          "dataReadCacheCallback"
        ],
        "in_edges": [
          151,
          152
        ],
        "out_edges": [
          154,
          155
        ],
        "weight": 5
      },
      "154": {
        "called_fns": [
          "dataReadCacheCallback"
        ],
        "in_edges": [
          153
        ],
        "out_edges": [
          140
        ],
        "weight": 2
      },
      "155": {
        "called_fns": [
          "dataWriteCacheCallback"
        ],
        "in_edges": [
          136,
          111,
          112,
          138,
          153
        ],
        "out_edges": [],
        "weight": 3
      }
    },
    "entry_block": 111,
    "loops": {},
    "returning_blocks": [
      155
    ]
  },
  "gop_pyramid": {
    "bbls": {
      "35": {
        "called_fns": [],
        "in_edges": [],
        "out_edges": [
          41,
          36
        ],
        "weight": 4
      },
      "36": {
        "called_fns": [],
        "in_edges": [
          35
        ],
        "out_edges": [
          39,
          37
        ],
        "weight": 3
      },
      "37": {
        "called_fns": [
          "gop_pyramid"
        ],
        "in_edges": [
          38,
          39,
          40,
          36
        ],
        "out_edges": [
          41,
          38
        ],
        "weight": 7
      },
      "38": {
        "called_fns": [],
        "in_edges": [
          37
        ],
        "out_edges": [
          39,
          37
        ],
        "weight": 1
      },
      "39": {
        "called_fns": [
          "dataReadCacheCallback",
          "dataReadCacheCallback"
        ],
        "in_edges": [
          38,
          36
        ],
        "out_edges": [
          40,
          37
        ],
        "weight": 2
      },
      "40": {
        "called_fns": [
          "dataWriteCacheCallback",
          "dataWriteCacheCallback",
          "dataWriteCacheCallback",
          "dataWriteCacheCallback"
        ],
        "in_edges": [
          39
        ],
        "out_edges": [
          37
        ],
        "weight": 8
      },
      "41": {
        "called_fns": [],
        "in_edges": [
          37,
          35
        ],
        "out_edges": [
          42,
          45
        ],
        "weight": 1
      },
      "42": {
        "called_fns": [
          "dataReadCacheCallback",
          "dataReadCacheCallback"
        ],
        "in_edges": [
          41
        ],
        "out_edges": [
          43,
          45
        ],
        "weight": 2
      },
      "43": {
        "called_fns": [
          "dataReadCacheCallback"
        ],
        "in_edges": [
          42
        ],
        "out_edges": [
          44,
          45
        ],
        "weight": 3
      },
      "44": {
        "called_fns": [
          "dataWriteCacheCallback",
          "dataWriteCacheCallback",
          "dataWriteCacheCallback",
          "dataWriteCacheCallback"
        ],
        "in_edges": [
          43
        ],
        "out_edges": [
          45
        ],
        "weight": 5
      },
      "45": {
        "called_fns": [],
        "in_edges": [
          41,
          42,
          43,
          44
        ],
        "out_edges": [],
        "weight": 2
      }
    },
    "entry_block": 35,
    "loops": {
      "5": {
        "loop_called_fns": [
          "dataReadCacheCallback",
          "dataWriteCacheCallback",
          "gop_pyramid"
        ],
        "loop_headers": [
          37,
          39
        ],
        "loop_latches": [
          38,
          39,
          40
        ]
      }
    },
    "returning_blocks": [
      45
    ]
  },
  "init_gop_structure": {
    "bbls": {
      "46": {
        "called_fns": [
          "dataReadCacheCallback",
          "dataReadCacheCallback",
          "dataReadCacheCallback",
          "calloc",
          "dataWriteCacheCallback"
        ],
        "in_edges": [],
        "out_edges": [
          48,
          47
        ],
        "weight": 9
      },
      "47": {
        "called_fns": [],
        "in_edges": [
          46
        ],
        "out_edges": [],
        "weight": 1
      },
      "48": {
        "called_fns": [
          "no_mem_exit"
        ],
        "in_edges": [
          46
        ],
        "out_edges": [],
        "weight": 2
      }
    },
    "entry_block": 46,
    "loops": {},
    "returning_blocks": [
      47,
      48
    ]
  },
  "interpret_gop_structure": {
    "bbls": {
      "100": {
        "called_fns": [],
        "in_edges": [
          98,
          99
        ],
        "out_edges": [
          56
        ],
        "weight": 1
      },
      "101": {
        "called_fns": [],
        "in_edges": [
          86,
          87
        ],
        "out_edges": [
          57
        ],
        "weight": 1
      },
      "102": {
        "called_fns": [],
        "in_edges": [
          83
        ],
        "out_edges": [
          106,
          103
        ],
        "weight": 1
      },
      "103": {
        "called_fns": [],
        "in_edges": [
          102
        ],
        "out_edges": [
          104,
          107
        ],
        "weight": 1
      },
      "104": {
        "called_fns": [
          "dataReadCacheCallback",
          "dataWriteCacheCallback"
        ],
        "in_edges": [
          103,
          84
        ],
        "out_edges": [
          108
        ],
        "weight": 4
      },
      "105": {
        "called_fns": [],
        "in_edges": [
          88,
          89
        ],
        "out_edges": [
          94
        ],
        "weight": 1
      },
      "106": {
        "called_fns": [
          "dataReadCacheCallback",
          "dataWriteCacheCallback"
        ],
        "in_edges": [
          102,
          85
        ],
        "out_edges": [
          108
        ],
        "weight": 4
      },
      "107": {
        "called_fns": [
          "error"
        ],
        "in_edges": [
          103,
          85
        ],
        "out_edges": [
          108
        ],
        "weight": 5
      },
      "108": {
        "called_fns": [],
        "in_edges": [
          104,
          107,
          106
        ],
        "out_edges": [
          56
        ],
        "weight": 1
      },
      "109": {
        "called_fns": [
          "error"
        ],
        "in_edges": [
          52
        ],
        "out_edges": [
          110
        ],
        "weight": 5
      },
      "110": {
        "called_fns": [
          "dataReadCacheCallback",
          "dataWriteCacheCallback"
        ],
        "in_edges": [
          109,
          57
        ],
        "out_edges": [],
        "weight": 5
      },
      "52": {
        "called_fns": [
          "dataReadCacheCallback",
          "strlen"
        ],
        "in_edges": [],
        "out_edges": [
          53,
          109
        ],
        "weight": 6
      },
      "53": {
        "called_fns": [],
        "in_edges": [
          52
        ],
        "out_edges": [
          58
        ],
        "weight": 4
      },
      "54": {
        "called_fns": [
          "error"
        ],
        "in_edges": [
          71
        ],
        "out_edges": [
          55
        ],
        "weight": 6
      },
      "55": {
        "called_fns": [],
        "in_edges": [
          94,
          54,
          96
        ],
        "out_edges": [
          56
        ],
        "weight": 1
      },
      "56": {
        "called_fns": [],
        "in_edges": [
          55,
          100,
          108,
          97
        ],
        "out_edges": [
          57
        ],
        "weight": 1
      },
      "57": {
        "called_fns": [],
        "in_edges": [
          101,
          81,
          80,
          70,
          95,
          92,
          60,
          56
        ],
        "out_edges": [
          58,
          110
        ],
        "weight": 1
      },
      "58": {
        "called_fns": [],
        "in_edges": [
          53,
          57
        ],
        "out_edges": [
          66,
          59
        ],
        "weight": 1
      },
      "59": {
        "called_fns": [],
        "in_edges": [
          58
        ],
        "out_edges": [
          71,
          60
        ],
        "weight": 1
      },
      "60": {
        "called_fns": [],
        "in_edges": [
          59
        ],
        "out_edges": [
          61,
          57
        ],
        "weight": 1
      },
      "61": {
        "called_fns": [],
        "in_edges": [
          60
        ],
        "out_edges": [
          82,
          62
        ],
        "weight": 1
      },
      "62": {
        "called_fns": [],
        "in_edges": [
          61
        ],
        "out_edges": [
          63,
          86
        ],
        "weight": 1
      },
      "63": {
        "called_fns": [],
        "in_edges": [
          62
        ],
        "out_edges": [
          64,
          86
        ],
        "weight": 1
      },
      "64": {
        "called_fns": [
          "__ctype_b_loc",
          "dataReadCacheCallback",
          "dataReadCacheCallback",
          "dataReadCacheCallback",
          "dataReadCacheCallback"
        ],
        "in_edges": [
          63
        ],
        "out_edges": [
          65,
          98
        ],
        "weight": 6
      },
      "65": {
        "called_fns": [
          "error"
        ],
        "in_edges": [
          64
        ],
        "out_edges": [
          94
        ],
        "weight": 6
      },
      "66": {
        "called_fns": [
          "dataReadCacheCallback",
          "dataReadCacheCallback"
        ],
        "in_edges": [
          58
        ],
        "out_edges": [
          95,
          67
        ],
        "weight": 4
      },
      "67": {
        "called_fns": [],
        "in_edges": [
          66
        ],
        "out_edges": [
          80,
          68
        ],
        "weight": 1
      },
      "68": {
        "called_fns": [],
        "in_edges": [
          67
        ],
        "out_edges": [
          81,
          69
        ],
        "weight": 1
      },
      "69": {
        "called_fns": [],
        "in_edges": [
          68
        ],
        "out_edges": [
          70,
          95
        ],
        "weight": 1
      },
      "70": {
        "called_fns": [
          "dataReadCacheCallback",
          "dataWriteCacheCallback"
        ],
        "in_edges": [
          69
        ],
        "out_edges": [
          57
        ],
        "weight": 3
      },
      "71": {
        "called_fns": [
          "__ctype_b_loc",
          "dataReadCacheCallback",
          "dataReadCacheCallback",
          "dataReadCacheCallback",
          "dataReadCacheCallback"
        ],
        "in_edges": [
          59
        ],
        "out_edges": [
          54,
          72
        ],
        "weight": 6
      },
      "72": {
        "called_fns": [
          "__isoc99_sscanf",
          "dataReadCacheCallback",
          "dataReadCacheCallback",
          "dataWriteCacheCallback",
          "dataReadCacheCallback",
          "dataReadCacheCallback",
          "dataReadCacheCallback"
        ],
        "in_edges": [
          71
        ],
        "out_edges": [
          73,
          74
        ],
        "weight": 10
      },
      "73": {
        "called_fns": [],
        "in_edges": [
          72
        ],
        "out_edges": [
          75,
          74
        ],
        "weight": 1
      },
      "74": {
        "called_fns": [
          "snprintf",
          "error"
        ],
        "in_edges": [
          72,
          73
        ],
        "out_edges": [
          75
        ],
        "weight": 4
      },
      "75": {
        "called_fns": [],
        "in_edges": [
          73,
          74
        ],
        "out_edges": [
          76,
          96
        ],
        "weight": 1
      },
      "76": {
        "called_fns": [],
        "in_edges": [
          75
        ],
        "out_edges": [
          78
        ],
        "weight": 3
      },
      "77": {
        "called_fns": [],
        "in_edges": [
          78,
          79
        ],
        "out_edges": [
          93,
          78
        ],
        "weight": 2
      },
      "78": {
        "called_fns": [
          "dataReadCacheCallback",
          "dataReadCacheCallback",
          "dataReadCacheCallback"
        ],
        "in_edges": [
          76,
          77
        ],
        "out_edges": [
          79,
          77
        ],
        "weight": 3
      },
      "79": {
        "called_fns": [
          "snprintf",
          "error"
        ],
        "in_edges": [
          78
        ],
        "out_edges": [
          77
        ],
        "weight": 4
      },
      "80": {
        "called_fns": [
          "dataReadCacheCallback",
          "dataWriteCacheCallback"
        ],
        "in_edges": [
          67
        ],
        "out_edges": [
          57
        ],
        "weight": 3
      },
      "81": {
        "called_fns": [
          "dataReadCacheCallback",
          "dataWriteCacheCallback"
        ],
        "in_edges": [
          68
        ],
        "out_edges": [
          57
        ],
        "weight": 3
      },
      "82": {
        "called_fns": [
          "__ctype_b_loc",
          "dataReadCacheCallback",
          "dataReadCacheCallback",
          "dataReadCacheCallback",
          "dataReadCacheCallback"
        ],
        "in_edges": [
          61
        ],
        "out_edges": [
          83,
          97
        ],
        "weight": 6
      },
      "83": {
        "called_fns": [],
        "in_edges": [
          82
        ],
        "out_edges": [
          84,
          102
        ],
        "weight": 1
      },
      "84": {
        "called_fns": [],
        "in_edges": [
          83
        ],
        "out_edges": [
          104,
          85
        ],
        "weight": 1
      },
      "85": {
        "called_fns": [],
        "in_edges": [
          84
        ],
        "out_edges": [
          106,
          107
        ],
        "weight": 1
      },
      "86": {
        "called_fns": [],
        "in_edges": [
          62,
          63
        ],
        "out_edges": [
          87,
          101
        ],
        "weight": 1
      },
      "87": {
        "called_fns": [],
        "in_edges": [
          86
        ],
        "out_edges": [
          88,
          101
        ],
        "weight": 1
      },
      "88": {
        "called_fns": [
          "__ctype_b_loc",
          "dataReadCacheCallback",
          "dataReadCacheCallback",
          "dataReadCacheCallback",
          "dataReadCacheCallback"
        ],
        "in_edges": [
          87
        ],
        "out_edges": [
          89,
          105
        ],
        "weight": 6
      },
      "89": {
        "called_fns": [],
        "in_edges": [
          88
        ],
        "out_edges": [
          90,
          105
        ],
        "weight": 1
      },
      "90": {
        "called_fns": [
          "dataReadCacheCallback"
        ],
        "in_edges": [
          89
        ],
        "out_edges": [
          92,
          91
        ],
        "weight": 4
      },
      "91": {
        "called_fns": [
          "error"
        ],
        "in_edges": [
          90
        ],
        "out_edges": [
          92
        ],
        "weight": 6
      },
      "92": {
        "called_fns": [],
        "in_edges": [
          90,
          91
        ],
        "out_edges": [
          57
        ],
        "weight": 2
      },
      "93": {
        "called_fns": [],
        "in_edges": [
          77
        ],
        "out_edges": [
          94
        ],
        "weight": 1
      },
      "94": {
        "called_fns": [],
        "in_edges": [
          93,
          105,
          65
        ],
        "out_edges": [
          55
        ],
        "weight": 1
      },
      "95": {
        "called_fns": [
          "error"
        ],
        "in_edges": [
          66,
          69
        ],
        "out_edges": [
          57
        ],
        "weight": 5
      },
      "96": {
        "called_fns": [],
        "in_edges": [
          75
        ],
        "out_edges": [
          55
        ],
        "weight": 1
      },
      "97": {
        "called_fns": [],
        "in_edges": [
          82
        ],
        "out_edges": [
          56
        ],
        "weight": 1
      },
      "98": {
        "called_fns": [
          "__isoc99_sscanf",
          "dataReadCacheCallback",
          "dataReadCacheCallback",
          "dataWriteCacheCallback",
          "dataReadCacheCallback"
        ],
        "in_edges": [
          64
        ],
        "out_edges": [
          99,
          100
        ],
        "weight": 8
      },
      "99": {
        "called_fns": [
          "error"
        ],
        "in_edges": [
          98
        ],
        "out_edges": [
          100
        ],
        "weight": 3
      }
    },
    "entry_block": 52,
    "loops": {
      "6": {
        "loop_called_fns": [
          "dataReadCacheCallback",
          "error",
          "snprintf"
        ],
        "loop_headers": [
          78
        ],
        "loop_latches": [
          77
        ]
      }
    },
    "returning_blocks": [
      110
    ]
  },
  "poc_based_ref_management": {
    "bbls": {
      "156": {
        "called_fns": [
          "dataReadCacheCallback",
          "dataReadCacheCallback"
        ],
        "in_edges": [],
        "out_edges": [
          157,
          171
        ],
        "weight": 5
      },
      "157": {
        "called_fns": [
          "dataReadCacheCallback",
          "dataReadCacheCallback"
        ],
        "in_edges": [
          156
        ],
        "out_edges": [
          171,
          158
        ],
        "weight": 3
      },
      "158": {
        "called_fns": [
          "dataReadCacheCallback"
        ],
        "in_edges": [
          157
        ],
        "out_edges": [
          165,
          159
        ],
        "weight": 2
      },
      "159": {
        "called_fns": [
          "dataReadCacheCallback"
        ],
        "in_edges": [
          158
        ],
        "out_edges": [
          161
        ],
        "weight": 5
      },
      "160": {
        "called_fns": [],
        "in_edges": [
          163,
          164,
          161,
          162
        ],
        "out_edges": [
          161,
          166
        ],
        "weight": 1
      },
      "161": {
        "called_fns": [
          "dataReadCacheCallback",
          "dataReadCacheCallback"
        ],
        "in_edges": [
          159,
          160
        ],
        "out_edges": [
          160,
          162
        ],
        "weight": 2
      },
      "162": {
        "called_fns": [
          "dataReadCacheCallback"
        ],
        "in_edges": [
          161
        ],
        "out_edges": [
          163,
          160
        ],
        "weight": 1
      },
      "163": {
        "called_fns": [
          "dataReadCacheCallback"
        ],
        "in_edges": [
          162
        ],
        "out_edges": [
          164,
          160
        ],
        "weight": 1
      },
      "164": {
        "called_fns": [
          "dataReadCacheCallback",
          "dataReadCacheCallback",
          "dataReadCacheCallback"
        ],
        "in_edges": [
          163
        ],
        "out_edges": [
          160
        ],
        "weight": 3
      },
      "165": {
        "called_fns": [],
        "in_edges": [
          158
        ],
        "out_edges": [
          166
        ],
        "weight": 1
      },
      "166": {
        "called_fns": [
          "calloc"
        ],
        "in_edges": [
          160,
          165
        ],
        "out_edges": [
          167,
          168
        ],
        "weight": 2
      },
      "167": {
        "called_fns": [
          "no_mem_exit"
        ],
        "in_edges": [
          166
        ],
        "out_edges": [
          168
        ],
        "weight": 1
      },
      "168": {
        "called_fns": [
          "dataWriteCacheCallback",
          "dataWriteCacheCallback",
          "calloc"
        ],
        "in_edges": [
          166,
          167
        ],
        "out_edges": [
          169,
          170
        ],
        "weight": 4
      },
      "169": {
        "called_fns": [
          "no_mem_exit"
        ],
        "in_edges": [
          168
        ],
        "out_edges": [
          170
        ],
        "weight": 1
      },
      "170": {
        "called_fns": [
          "dataWriteCacheCallback",
          "dataWriteCacheCallback",
          "dataWriteCacheCallback",
          "dataReadCacheCallback",
          "dataWriteCacheCallback"
        ],
        "in_edges": [
          168,
          169
        ],
        "out_edges": [
          171
        ],
        "weight": 7
      },
      "171": {
        "called_fns": [],
        "in_edges": [
          156,
          157,
          170
        ],
        "out_edges": [],
        "weight": 2
      }
    },
    "entry_block": 156,
    "loops": {
      "7": {
        "loop_called_fns": [
          "dataReadCacheCallback"
        ],
        "loop_headers": [
          161
        ],
        "loop_latches": [
          160
        ]
      }
    },
    "returning_blocks": [
      171
    ]
  }
}
