{
	"overheads":	[{
			"idx":	0,
			"elapsedSec":	127.62425994873047
		}, {
			"idx":	1,
			"elapsedSec":	128.989990234375
		}, {
			"idx":	2,
			"elapsedSec":	129.6998291015625
		}, {
			"idx":	3,
			"elapsedSec":	130.13131713867188
		}, {
			"idx":	4,
			"elapsedSec":	129.57597351074219
		}, {
			"idx":	5,
			"elapsedSec":	128.91180419921875
		}, {
			"idx":	6,
			"elapsedSec":	129.2357177734375
		}, {
			"idx":	7,
			"elapsedSec":	128.92816162109375
		}, {
			"idx":	8,
			"elapsedSec":	130.57034301757812
		}, {
			"idx":	9,
			"elapsedSec":	129.30947875976562
		}],
	"burst_lengths":	[{
			"idx":	0,
			"mu_progress_duration":	0,
			"std_progress_duration":	0,
			"num_appts":	100999980
		}, {
			"idx":	1,
			"mu_progress_duration":	1.9960057735443115,
			"std_progress_duration":	0.0630752816796303,
			"num_appts":	5049999
		}, {
			"idx":	2,
			"mu_progress_duration":	1.996006965637207,
			"std_progress_duration":	0.063063941895961761,
			"num_appts":	5049999
		}, {
			"idx":	3,
			"mu_progress_duration":	1.9960078001022339,
			"std_progress_duration":	0.063054487109184265,
			"num_appts":	5049999
		}, {
			"idx":	4,
			"mu_progress_duration":	1.9960078001022339,
			"std_progress_duration":	0.063054487109184265,
			"num_appts":	5049999
		}, {
			"idx":	5,
			"mu_progress_duration":	1.99600625038147,
			"std_progress_duration":	0.0630677193403244,
			"num_appts":	5049999
		}, {
			"idx":	6,
			"mu_progress_duration":	1.9960057735443115,
			"std_progress_duration":	0.0630752816796303,
			"num_appts":	5049999
		}, {
			"idx":	7,
			"mu_progress_duration":	1.996006965637207,
			"std_progress_duration":	0.063063941895961761,
			"num_appts":	5049999
		}, {
			"idx":	8,
			"mu_progress_duration":	1.9960057735443115,
			"std_progress_duration":	0.0630752816796303,
			"num_appts":	5049999
		}, {
			"idx":	9,
			"mu_progress_duration":	1.9960074424743652,
			"std_progress_duration":	0.063060157001018524,
			"num_appts":	5049999
		}, {
			"idx":	10,
			"mu_progress_duration":	1.9960074424743652,
			"std_progress_duration":	0.063060157001018524,
			"num_appts":	5049999
		}, {
			"idx":	11,
			"mu_progress_duration":	1.9960057735443115,
			"std_progress_duration":	0.0630752816796303,
			"num_appts":	5049999
		}, {
			"idx":	12,
			"mu_progress_duration":	1.99600625038147,
			"std_progress_duration":	0.0630677193403244,
			"num_appts":	5049999
		}, {
			"idx":	13,
			"mu_progress_duration":	1.9960074424743652,
			"std_progress_duration":	0.063060157001018524,
			"num_appts":	5049999
		}, {
			"idx":	14,
			"mu_progress_duration":	1.9960074424743652,
			"std_progress_duration":	0.063060157001018524,
			"num_appts":	5049999
		}, {
			"idx":	15,
			"mu_progress_duration":	1.9960057735443115,
			"std_progress_duration":	0.0630752816796303,
			"num_appts":	5049999
		}, {
			"idx":	16,
			"mu_progress_duration":	1.99600625038147,
			"std_progress_duration":	0.0630677193403244,
			"num_appts":	5049999
		}, {
			"idx":	17,
			"mu_progress_duration":	1.99600625038147,
			"std_progress_duration":	0.0630677193403244,
			"num_appts":	5049999
		}, {
			"idx":	18,
			"mu_progress_duration":	1.9960057735443115,
			"std_progress_duration":	0.0630752816796303,
			"num_appts":	5049999
		}, {
			"idx":	19,
			"mu_progress_duration":	1.9960078001022339,
			"std_progress_duration":	0.063054487109184265,
			"num_appts":	5049999
		}, {
			"idx":	20,
			"mu_progress_duration":	1.9960081577301025,
			"std_progress_duration":	0.0630563795566559,
			"num_appts":	5049999
		}]
}