{
	"overheads":	[{
			"idx":	0,
			"elapsedSec":	214.71633911132812
		}, {
			"idx":	1,
			"elapsedSec":	214.88031005859375
		}, {
			"idx":	2,
			"elapsedSec":	214.76510620117188
		}, {
			"idx":	3,
			"elapsedSec":	216.32759094238281
		}, {
			"idx":	4,
			"elapsedSec":	221.26429748535156
		}],
	"burst_lengths":	[{
			"idx":	0,
			"mu_progress_duration":	0,
			"std_progress_duration":	0,
			"num_appts":	22949991
		}, {
			"idx":	1,
			"mu_progress_duration":	1.9959888458251953,
			"std_progress_duration":	0.0632074400782585,
			"num_appts":	2549999
		}, {
			"idx":	2,
			"mu_progress_duration":	1.9960075616836548,
			"std_progress_duration":	0.063060157001018524,
			"num_appts":	2549999
		}, {
			"idx":	3,
			"mu_progress_duration":	1.9960083961486816,
			"std_progress_duration":	0.063052594661712646,
			"num_appts":	2549999
		}, {
			"idx":	4,
			"mu_progress_duration":	1.9960075616836548,
			"std_progress_duration":	0.063060157001018524,
			"num_appts":	2549999
		}, {
			"idx":	5,
			"mu_progress_duration":	1.9960083961486816,
			"std_progress_duration":	0.063052594661712646,
			"num_appts":	2549999
		}, {
			"idx":	6,
			"mu_progress_duration":	1.9960083961486816,
			"std_progress_duration":	0.063052594661712646,
			"num_appts":	2549999
		}, {
			"idx":	7,
			"mu_progress_duration":	1.9960068464279175,
			"std_progress_duration":	0.063063941895961761,
			"num_appts":	2549999
		}, {
			"idx":	8,
			"mu_progress_duration":	1.9960068464279175,
			"std_progress_duration":	0.063063941895961761,
			"num_appts":	2549999
		}, {
			"idx":	9,
			"mu_progress_duration":	1.9960083961486816,
			"std_progress_duration":	0.063052594661712646,
			"num_appts":	2549999
		}]
}